odoo/addons/sale_order_discount_invoicing/README.rst
odoo/addons/sale_order_discount_invoicing/__init__.py
odoo/addons/sale_order_discount_invoicing/__manifest__.py
odoo/addons/sale_order_discount_invoicing/i18n/es.po
odoo/addons/sale_order_discount_invoicing/i18n/fr.po
odoo/addons/sale_order_discount_invoicing/i18n/sale_order_discount_invoicing.pot
odoo/addons/sale_order_discount_invoicing/models/__init__.py
odoo/addons/sale_order_discount_invoicing/models/account_move.py
odoo/addons/sale_order_discount_invoicing/models/account_move_line.py
odoo/addons/sale_order_discount_invoicing/models/product_category.py
odoo/addons/sale_order_discount_invoicing/models/product_template.py
odoo/addons/sale_order_discount_invoicing/models/res_company.py
odoo/addons/sale_order_discount_invoicing/models/res_config_settings.py
odoo/addons/sale_order_discount_invoicing/models/sale_order_line.py
odoo/addons/sale_order_discount_invoicing/readme/CONFIGURE.rst
odoo/addons/sale_order_discount_invoicing/readme/DESCRIPTION.rst
odoo/addons/sale_order_discount_invoicing/readme/USAGE.rst
odoo/addons/sale_order_discount_invoicing/static/description/icon.png
odoo/addons/sale_order_discount_invoicing/static/description/index.html
odoo/addons/sale_order_discount_invoicing/tests/__init__.py
odoo/addons/sale_order_discount_invoicing/tests/test_sale_discount.py
odoo/addons/sale_order_discount_invoicing/views/product_category.xml
odoo/addons/sale_order_discount_invoicing/views/product_template.xml
odoo/addons/sale_order_discount_invoicing/views/res_config_settings.xml
odoo/addons/sale_order_discount_invoicing/views/sale_order.xml
odoo_addon_sale_order_discount_invoicing-15.0.1.0.0.10.dist-info/METADATA
odoo_addon_sale_order_discount_invoicing-15.0.1.0.0.10.dist-info/WHEEL
odoo_addon_sale_order_discount_invoicing-15.0.1.0.0.10.dist-info/top_level.txt
odoo_addon_sale_order_discount_invoicing-15.0.1.0.0.10.dist-info/RECORD
